{
    "data": [
        {
            "id": 1,
            "name": "Jane Doe",
            "image": "https://picsum.photos/600/850/?image=817",
            "filter": "_1977",
            "caption": "Let me take a nap... great shot, anyway."
        },
        {
            "id": 2,
            "name": "Abida Sims",
            "image": "https://picsum.photos/600/850/?image=923",
            "filter": "aden",
            "caption": "Fabulous!! I approve the use of avatar and style!"
        },
        {
            "id": 3,
            "name": "Myrtle Terrell",
            "image": "https://picsum.photos/600/850/?image=1082",
            "filter": "brannan",
            "caption": "So neat and elegant!"
        },
        {
            "id": 4,
            "name": "Ismail Macdonald",
            "image": "https://picsum.photos/600/850/?image=1075",
            "filter": "brooklyn",
            "caption": "Such shot, many style, so bold"
        },
        {
            "id": 5,
            "name": "Shakir Chase",
            "image": "https://picsum.photos/600/850/?image=1067",
            "filter": "clarendon",
            "caption": "I think I'm crying. It's that excellent."
        },
        {
            "id": 6,
            "name": "Anne Liu",
            "image": "https://picsum.photos/600/850/?image=1062",
            "filter": "earlybird",
            "caption": "Light. Mmh wondering if this comment will hit the generateor as well..."
        },
        {
            "id": 7,
            "name": "Louie Knapp",
            "image": "https://picsum.photos/600/850/?image=1051",
            "filter": "gingham",
            "caption": "This shapes blew my mind."
        },
        {
            "id": 8,
            "name": "Neha Nolan",
            "image": "https://picsum.photos/600/850/?image=1033",
            "filter": "hudson",
            "caption": "Very thought out! Ahhhhhhh..."
        }
    ]
}
